fetchai/__init__.py
fetchai/ledger/__init__.py
fetchai/ledger/bitvector.py
fetchai/ledger/contract.py
fetchai/ledger/decode.py
fetchai/ledger/transaction.py
fetchai/ledger/api/__init__.py
fetchai/ledger/api/bootstrap.py
fetchai/ledger/api/common.py
fetchai/ledger/api/contracts.py
fetchai/ledger/api/governance.py
fetchai/ledger/api/server.py
fetchai/ledger/api/token.py
fetchai/ledger/api/tx.py
fetchai/ledger/crypto/__init__.py
fetchai/ledger/crypto/address.py
fetchai/ledger/crypto/deed.py
fetchai/ledger/crypto/entity.py
fetchai/ledger/crypto/identity.py
fetchai/ledger/parser/__init__.py
fetchai/ledger/parser/etch.grammar
fetchai/ledger/parser/etch_parser.py
fetchai/ledger/serialisation/__init__.py
fetchai/ledger/serialisation/address.py
fetchai/ledger/serialisation/bytearray.py
fetchai/ledger/serialisation/identity.py
fetchai/ledger/serialisation/integer.py
fetchai/ledger/serialisation/sha256.py
fetchai/ledger/serialisation/shardmask.py
fetchai/ledger/serialisation/transaction.py
tests/api/__init__.py
tests/api/test_bootstrap.py
tests/api/test_server.py
tests/api/test_token.py
tests/api/test_tx_contents.py
tests/api/test_tx_status.py
tests/api/test_version_compatibility.py
tests/crypto/__init__.py
tests/crypto/test_address.py
tests/crypto/test_deed.py
tests/crypto/test_encryption.py
tests/crypto/test_entity.py
tests/crypto/test_identity.py
tests/crypto/test_shard_mask.py
tests/parser/__init__.py
tests/parser/test_parser.py
tests/parser/test_shard_mask_parsing.py
tests/serialisation/__init__.py
tests/serialisation/common.py
tests/serialisation/test_address.py
tests/serialisation/test_bytearray.py
tests/serialisation/test_identity.py
tests/serialisation/test_integer.py
tests/serialisation/test_transaction.py
fetchai_ledger_api-1.1.0.dist-info/LICENSE
fetchai_ledger_api-1.1.0.dist-info/METADATA
fetchai_ledger_api-1.1.0.dist-info/WHEEL
fetchai_ledger_api-1.1.0.dist-info/top_level.txt
fetchai_ledger_api-1.1.0.dist-info/RECORD
