Metadata-Version: 2.1
Name: fetchai-ledger-api
Version: 1.1.0
Summary: Tools and utilities for interacting with the ledger on the fetch network
Home-page: https://github.com/fetchai/ledger-api-py
Author: Edward FitzGerald
Author-email: edward.fitzgerald@fetch.ai
License: UNKNOWN
Project-URL: Bug Reports, https://github.com/fetchai/ledger-api-py/issues
Project-URL: Developer Site, https://developer.fetch.ai/
Project-URL: Documentation, https://docs.fetch.ai/
Project-URL: Source, https://github.com/fetchai/ledger-api-py
Platform: UNKNOWN
Classifier: Programming Language :: Python :: 3 :: Only
Classifier: Programming Language :: Python :: 3.5
Classifier: Programming Language :: Python :: 3.6
Classifier: Programming Language :: Python :: 3.7
Classifier: Programming Language :: Python :: 3.8
Requires-Python: >=3.5
Provides-Extra: dev
Provides-Extra: test
